Changelog
MANIFEST.in
README
setup.cfg
setup.py
bin/cgutil
cgroup_utils.egg-info/PKG-INFO
cgroup_utils.egg-info/SOURCES.txt
cgroup_utils.egg-info/dependency_links.txt
cgroup_utils.egg-info/requires.txt
cgroup_utils.egg-info/top_level.txt
cgutils/__init__.py
cgutils/cgroup.py
cgutils/command.py
cgutils/fileops.py
cgutils/formatter.py
cgutils/host.py
cgutils/linux.c
cgutils/process.py
cgutils/version.py
cgutils/commands/__init__.py
cgutils/commands/configs.py
cgutils/commands/event.py
cgutils/commands/mkdir.py
cgutils/commands/pgrep.py
cgutils/commands/rmdir.py
cgutils/commands/stats.py
cgutils/commands/top.py
cgutils/commands/tree.py