Metadata-Version: 2.1
Name: cgroup-utils
Version: 0.6
Summary: Utility tools for control groups of Linux
Home-page: https://github.com/peo3/cgroup-utils
Author: peo3
Author-email: peo314159265@gmail.com
License: GPLv2
Platform: UNKNOWN
Classifier: Development Status :: 4 - Beta
Classifier: Environment :: Console
Classifier: Intended Audience :: System Administrators
Classifier: License :: OSI Approved :: GNU General Public License v2 (GPLv2)
Classifier: Operating System :: POSIX :: Linux
Classifier: Programming Language :: C
Classifier: Programming Language :: Python
Classifier: Topic :: System :: Operating System Kernels :: Linux
Classifier: Topic :: System :: Systems Administration
Classifier: Topic :: Utilities
Provides-Extra: test
